lnschema_core/__init__.py
lnschema_core/fields.py
lnschema_core/ids.py
lnschema_core/mocks.py
lnschema_core/models.py
lnschema_core/types.py
lnschema_core/users.py
lnschema_core/validation.py
lnschema_core/migrations/0052_squashed.py
lnschema_core/migrations/0053_alter_featureset_hash_alter_paramvalue_created_by_and_more.py
lnschema_core/migrations/0054_alter_feature_previous_runs_and_more.py
lnschema_core/migrations/0055_artifact_type_artifactparamvalue_and_more.py
lnschema_core/migrations/0056_rename_ulabel_ref_is_name_artifactulabel_label_ref_is_name_and_more.py
lnschema_core/migrations/0057_link_models_latest_report_and_others.py
lnschema_core/migrations/0058_artifact__actions_collection__actions.py
lnschema_core/migrations/0059_alter_artifact__accessor_alter_artifact__hash_type_and_more.py
lnschema_core/migrations/0060_alter_artifact__actions.py
lnschema_core/migrations/0061_alter_collection_meta_artifact_alter_run_environment_and_more.py
lnschema_core/migrations/0062_add_is_latest_field.py
lnschema_core/migrations/0063_populate_latest_field.py
lnschema_core/migrations/0064_alter_artifact_version_alter_collection_version_and_more.py
lnschema_core/migrations/0065_remove_collection_feature_sets_and_more.py
lnschema_core/migrations/0066_alter_artifact__feature_values_and_more.py
lnschema_core/migrations/0067_alter_featurevalue_unique_together_and_more.py
lnschema_core/migrations/0068_alter_artifactulabel_unique_together_and_more.py
lnschema_core/migrations/0069_alter_artifact__accessor_alter_artifact__hash_type_and_more.py
lnschema_core/migrations/0069_squashed.py
lnschema_core/migrations/__init__.py
lnschema_core-0.77.1.dist-info/LICENSE
lnschema_core-0.77.1.dist-info/WHEEL
lnschema_core-0.77.1.dist-info/METADATA
lnschema_core-0.77.1.dist-info/RECORD
