Metadata-Version: 2.1
Name: lnschema_core
Version: 0.77.1
Summary: LaminDB's core registries.
Author-email: Lamin Labs <open-source@lamin.ai>
Classifier: License :: OSI Approved :: Apache Software License
Classifier: Programming Language :: Python :: 3.9
Classifier: Programming Language :: Python :: 3.10
Classifier: Programming Language :: Python :: 3.11
Requires-Dist: pre-commit ; extra == "dev"
Requires-Dist: nox ; extra == "dev"
Requires-Dist: laminci ; extra == "dev"
Requires-Dist: pytest>=6.0 ; extra == "dev"
Requires-Dist: pytest-cov ; extra == "dev"
Requires-Dist: nbproject-test ; extra == "dev"
Requires-Dist: pandas ; extra == "dev"
Project-URL: Home, https://github.com/laminlabs/lnschema-core
Provides-Extra: dev
